guardrails_detector_common/__init__.py
guardrails_detector_common/app.py
guardrails_detector_common/log_conf.yaml
guardrails_detector_common/scheme.py
guardrails_detector_common-0.1.0.dist-info/METADATA
guardrails_detector_common-0.1.0.dist-info/WHEEL
guardrails_detector_common-0.1.0.dist-info/licenses/LICENSE
guardrails_detector_common-0.1.0.dist-info/RECORD
